{
  "title": "Why care about Focus?",
  "subtitle": "The key to building apps that work everywhere.",
  "slideType": "LEFT_TEXT_RIGHT_IMAGE",
  "leftBullets": [
    {
      "title": "It's the **cursor for your keyboard**",
      "description": "Telling your app which widget is active and ready for input."
    },
    {
      "title": "Build for Everyone",
      "description": "Proper focus management is non-negotiable for accessibility, making apps usable with assistive tech."
    },
    {
      "title": "Power Up Desktop & Web",
      "description": "Go beyond the mouse with intuitive tab-based navigation and powerful keyboard shortcuts."
    },
    {
      "title": "Conquer the 10-Foot Experience",
      "description": "On TV, focus isn't just a feature—it's the **entire user interface**."
    }
  ],
  "rightImagePath": "assets/images/slides/2_why_care.png"
}
